{"sidebar_default":{"text-4":{"title":"","text":"<div class=\"cmsmasters_mailpoet_custom\">\r\n<h3>Subscribe and get the latest beauty news in your inbox<\/h3>\r\n[cmsmasters_mailpoet shortcode_id=\"loacfh125i\" form_id=\"1\" animation_delay=\"0\"]\r\n\r\n<\/div>","filter":true,"visual":true},"categories-2":{"title":"","count":0,"hierarchical":0,"dropdown":1},"custom-profile-4":{"image":1,"name":0,"excerpt":1,"social":1,"title":"HELLO & WELCOME!","id":"446"}},"sidebar_bottom":{"nav_menu-6":{"title":"OUR WORLD","nav_menu":74},"nav_menu-3":{"title":"CUSTOMER SERVICE","nav_menu":75},"text-2":{"title":"SUBSCRIBE AND GET THE LATEST BEAUTY NEWS IN YOUR INBOX","text":"[cmsmasters_mailpoet shortcode_id=\"loacfh125i\" form_id=\"1\" animation_delay=\"0\"]","filter":true,"visual":true},"nav_menu-5":{"title":"SOCIAL","nav_menu":76}},"widget-home-5":{"custom-profile-3":{"image":1,"name":0,"excerpt":1,"social":1,"title":"HELLO & WELCOME!","id":"446"},"categories-5":{"title":"","count":1,"hierarchical":0,"dropdown":0}},"widget-faq":{"custom-latest-posts-3":{"title":"MOST POPULAR","number":4}},"widget-home":{"custom-profile-2":{"image":1,"name":1,"excerpt":0,"social":1,"title":"HELLO & WELCOME!","id":""},"categories-6":{"title":"CATEGORIES","count":1,"hierarchical":0,"dropdown":0},"custom-latest-posts-2":{"title":"MOST POPULAR","number":4},"archives-2":{"title":"ARCHIVES","count":0,"dropdown":1}},"sidebar_shop":{"search-2":{"title":"PRODUCT SEARCH"},"woocommerce_product_categories-2":{"title":"PRODUCT CATEGORIES","orderby":"name","dropdown":1,"count":0,"hierarchical":0,"show_children_only":0,"hide_empty":0,"max_depth":""},"woocommerce_price_filter-2":{"title":"FILTER BY PRICE"},"woocommerce_products-2":{"title":"PRODUCTS","number":3,"show":"","orderby":"date","order":"desc","hide_free":0,"show_hidden":0},"woocommerce_widget_cart-2":{"title":"CART","hide_if_empty":0}}}